react_component_generator/__init__.py
react_component_generator/cli.py
tests/__init__.py
tests/tests_cli.py
react_component_generator-0.1.0.dist-info/LICENSE
react_component_generator-0.1.0.dist-info/METADATA
react_component_generator-0.1.0.dist-info/WHEEL
react_component_generator-0.1.0.dist-info/entry_points.txt
react_component_generator-0.1.0.dist-info/top_level.txt
react_component_generator-0.1.0.dist-info/RECORD
