Metadata-Version: 2.1
Name: react-component-generator
Version: 0.1.0
Summary: A CLI tool for generating React components
Home-page: https://github.com/pylds/react-component-generator
Author: Damian Ledesma
Author-email: DamianLedesma@protonmail.com
Classifier: Programming Language :: Python :: 3
Classifier: License :: OSI Approved :: MIT License
Classifier: Operating System :: OS Independent
Requires-Python: >=3.6
License-File: LICENSE
Requires-Dist: rich>=13.0.0
Requires-Dist: typer
